{
  "musicas": {
    "musica01": {
      "id": "musica01",
      "nome": "Nome da musica",
      "ano": "1980",
      "genero": "rock"
    },
    "musica02": {
      "id": "musica02",
      "nome": "Uma música 2",
      "ano": "2016",
      "genero": "pop"
    },
    "musica03": {
      "nome": "Limao 3",
      "id": "musica03",
      "genero": "rock",
      "ano": "2020"
    },
    "musica04": {
      "id": "musica04",
      "nome": "Uma musica",
      "ano": "2023",
      "genero": "rock"
    }
  },
  "frutas": {
    "banana": {
      "nome": "Banana",
      "emoji": "🍌"
    },
    "limao": {
      "nome": "Limao 3",
      "emoji": "🍋",
      "id": "limao"
    },
    "uva": {
      "nome": "uva",
      "emoji": "🍇",
      "id": "uva"
    },
    "morango": {
      "nome": "Morango",
      "emoji": "🍓",
      "id": "morango"
    }
  },
  "filmes": {
    "filme01": {
      "id": "filme01",
      "nome": "O vento levou",
      "ano": "1960",
      "genero": "romance"
    },
    "filme02": {
      "id": "filme02",
      "nome": "De volta p/ futuro",
      "ano": "1980",
      "genero": "aventura"
    },
    "filme03": {
      "id": "filme03",
      "nome": "Rambo II",
      "ano": "1980",
      "genero": "aventura"
    },
    "filme05": {
      "id": "filme05",
      "nome": "Um nome de filme",
      "genero": "aventura",
      "ano": "2022"
    },
    "filme07": {
      "id": "filme07",
      "nome": "Um filme",
      "genero": "ação",
      "ano": "2000"
    }
  },
  "users": {
    "admin": {
      "id": "admin",
      "nome": "Administrador",
      "username": "admin",
      "password": "4742aa4e8d62801e931ff6783078bd2e163daf28e430595e2008a62310fc3b40BDEDc3xfWQjLSwgEBTgCLA==94b203e3f54e2955fe7f0197774125515f2b812a3b10bd804d335bacbc02f6fe"
    }
  }
}